MANIFEST.in
setup.py
mdemos/__init__.py
mdemos.menus.egg-info/PKG-INFO
mdemos.menus.egg-info/SOURCES.txt
mdemos.menus.egg-info/dependency_links.txt
mdemos.menus.egg-info/entry_points.txt
mdemos.menus.egg-info/namespace_packages.txt
mdemos.menus.egg-info/not-zip-safe
mdemos.menus.egg-info/requires.txt
mdemos.menus.egg-info/top_level.txt
mdemos/menus/__init__.py
mdemos/menus/default.py
mdemos/menus/widgets.py
mdemos/menus/controllers/__init__.py
mdemos/menus/controllers/menu.py
mdemos/menus/public/Powered-by-moksha_button.png
mdemos/menus/public/block.png
mdemos/menus/public/error.png
mdemos/menus/public/fedora-icon.png
mdemos/menus/public/gears.png
mdemos/menus/public/grad_blue_7x80.png
mdemos/menus/public/info.png
mdemos/menus/public/line.png
mdemos/menus/public/moksha-icon.png
mdemos/menus/public/moksha-logo-small.png
mdemos/menus/public/moksha-logo.png
mdemos/menus/public/ok.png
mdemos/menus/public/star.png
mdemos/menus/public/strype2.png
mdemos/menus/public/tg_under_the_hood.png
mdemos/menus/public/under_the_hood_blue.png
mdemos/menus/static/GPL-LICENSE.txt
mdemos/menus/static/mbMenu.js
mdemos/menus/static/mbMenu.min.js
mdemos/menus/static/styleswitch.js
mdemos/menus/static/css/menu.css
mdemos/menus/static/css/menu1.css
mdemos/menus/static/images/0682.gif
mdemos/menus/static/images/16-member-remove.png
mdemos/menus/static/images/24-book-blue-check.png
mdemos/menus/static/images/24-image-add.png
mdemos/menus/static/images/24-tag-add.png
mdemos/menus/static/images/Applet.gif
mdemos/menus/static/images/DV_Tools.jpg
mdemos/menus/static/images/bgColor.gif
mdemos/menus/static/images/bgnd_sel_1.jpg
mdemos/menus/static/images/bgnd_sel_2.jpg
mdemos/menus/static/images/bgnd_sel_3.jpg
mdemos/menus/static/images/bgnd_sel_4.png
mdemos/menus/static/images/blank.gif
mdemos/menus/static/images/browser.png
mdemos/menus/static/images/buttonfind.gif
mdemos/menus/static/images/header_bgnd.jpg
mdemos/menus/static/images/ico_view.gif
mdemos/menus/static/images/iconDone.png
mdemos/menus/static/images/icon_13.png
mdemos/menus/static/images/icon_14.png
mdemos/menus/static/images/menuArrow.gif
mdemos/menus/static/images/menuArrow_w.gif
mdemos/menus/templates/__init__.py
mdemos/menus/templates/__init__.pyc
mdemos/menus/templates/mbmenu.mak