Metadata-Version: 1.0
Name: mdemos.menus
Version: 1.0.2
Summary: Moksha Menus App
Home-page: http://moksha.fedorahosted.org
Author: Luke Macken
Author-email: lmacken@redhat.com
License: ASL 2.0
Platform: UNKNOWN
